lamber/__init__.py
lamber/hooks.py
lamber/main.py
lamber/models.py
lamber/sqlite.py
lamber/sqlite_create_tables.sql
lamber/utils.py
lamber-0.1.1.dist-info/METADATA
lamber-0.1.1.dist-info/WHEEL
lamber-0.1.1.dist-info/entry_points.txt
lamber-0.1.1.dist-info/licenses/LICENSE.txt
lamber-0.1.1.dist-info/RECORD
