Metadata-Version: 2.4
Name: lamber
Version: 0.1.1
Summary: An easy-to-use testing framework based on pytest
Author-email: luizyao <luizyao@163.com>
License-File: LICENSE.txt
Requires-Python: >=3.10
Requires-Dist: pytest>=8.3.5
